AUTHORS.rst
CHANGES.rst
MANIFEST.in
README.rst
TODO.rst
setup.cfg
setup.py
bird_feeder.egg-info/PKG-INFO
bird_feeder.egg-info/SOURCES.txt
bird_feeder.egg-info/dependency_links.txt
bird_feeder.egg-info/entry_points.txt
bird_feeder.egg-info/not-zip-safe
bird_feeder.egg-info/pbr.json
bird_feeder.egg-info/requires.txt
bird_feeder.egg-info/top_level.txt
birdfeeder/__init__.py
birdfeeder/client.py
birdfeeder/parser.py
unit_tests/__init__.py
unit_tests/test_parser.py