Metadata-Version: 1.1
Name: bird-feeder
Version: 0.1.2
Summary: Bird Feeder publishes Thredds metadata catalogs to a Solr index service with birdhouse schema.
Home-page: https://github.com/bird-house/bird-feeder
Author: Birdhouse Developers
Author-email: UNKNOWN
License: Apache License v2.0
Keywords: thredds solr python netcdf birdhouse anaconda
Platform: UNKNOWN
Classifier: Development Status :: 3 - Alpha
Classifier: Intended Audience :: Science/Research
Classifier: Operating System :: MacOS :: MacOS X
Classifier: Operating System :: Microsoft :: Windows
Classifier: Operating System :: POSIX
Classifier: Programming Language :: Python
Classifier: Topic :: Scientific/Engineering :: Atmospheric Science
